llmakits/__init__.py
llmakits/dash_client.py
llmakits/dispatcher.py
llmakits/dispatcher_control.py
llmakits/llm_client.py
llmakits/load_model.py
llmakits/e_commerce/__init__.py
llmakits/e_commerce/kit.py
llmakits/e_commerce/kits/__init__.py
llmakits/e_commerce/kits/attribute_kit.py
llmakits/e_commerce/kits/cat_kit.py
llmakits/e_commerce/kits/des_kit.py
llmakits/e_commerce/kits/title_kit.py
llmakits/e_commerce/kits/category/__init__.py
llmakits/e_commerce/kits/category/predictor.py
llmakits/e_commerce/kits/category/tokenizer.py
llmakits/e_commerce/kits/category/utils.py
llmakits/e_commerce/kits/category/validator.py
llmakits/e_commerce/validators/__init__.py
llmakits/e_commerce/validators/html_validator.py
llmakits/e_commerce/validators/string_validator.py
llmakits/e_commerce/validators/value_validator.py
llmakits/message/__init__.py
llmakits/message/builder.py
llmakits/message/formatter.py
llmakits/message/validator.py
llmakits/utils/__init__.py
llmakits/utils/image_cache.py
llmakits/utils/retry_config.py
llmakits/utils/retry_handler.py
llmakits-0.6.27.dist-info/licenses/LICENSE
llmakits-0.6.27.dist-info/METADATA
llmakits-0.6.27.dist-info/WHEEL
llmakits-0.6.27.dist-info/top_level.txt
llmakits-0.6.27.dist-info/RECORD
