Metadata-Version: 2.4
Name: llmakits
Version: 0.6.27
Summary: A powerful Python toolkit for simplifying LLM integration and management with multi-model scheduling, fault tolerance, and load balancing support
Home-page: https://github.com/tinycen/llmakits
Author: tinycen
Author-email: sky_ruocen@qq.com
Project-URL: Source, https://github.com/tinycen/llmakits
Project-URL: Documentation, https://github.com/tinycen/llmakits#readme
Project-URL: Bug Reports, https://github.com/tinycen/llmakits/issues
Keywords: llm,ai,chatgpt,openai,zhipu,dashscope,modelscope,multi-model,scheduling,fault-tolerance
Classifier: Development Status :: 4 - Beta
Classifier: Intended Audience :: Developers
Classifier: License :: OSI Approved :: Apache Software License
Classifier: Operating System :: OS Independent
Classifier: Programming Language :: Python :: 3
Classifier: Programming Language :: Python :: 3.10
Classifier: Programming Language :: Python :: 3.11
Classifier: Programming Language :: Python :: 3.12
Classifier: Topic :: Software Development :: Libraries :: Python Modules
Classifier: Topic :: Scientific/Engineering :: Artificial Intelligence
Classifier: Topic :: Text Processing :: Linguistic
Requires-Python: >=3.10
License-File: LICENSE
Requires-Dist: regex
Requires-Dist: pyyaml
Requires-Dist: pandas
Requires-Dist: openai
Requires-Dist: zhipuai
Requires-Dist: dashscope
Requires-Dist: filekits
Requires-Dist: funcguard
Requires-Dist: ollama>=0.6.0
Provides-Extra: dev
Requires-Dist: pytest>=6.0; extra == "dev"
Requires-Dist: pytest-cov>=2.0; extra == "dev"
Requires-Dist: black>=21.0; extra == "dev"
Requires-Dist: flake8>=3.8; extra == "dev"
Requires-Dist: mypy>=0.812; extra == "dev"
Dynamic: author
Dynamic: author-email
Dynamic: classifier
Dynamic: description
Dynamic: description-content-type
Dynamic: home-page
Dynamic: keywords
Dynamic: license-file
Dynamic: project-url
Dynamic: provides-extra
Dynamic: requires-dist
Dynamic: requires-python
Dynamic: summary
